<?xml version="1.0" encoding="UTF-8"?>

<container xmlns="http://symfony.com/schema/dic/services"
    xmlns:xsi="http://www.w3.org/2001/XMLSchema-instance"
    xsi:schemaLocation="http://symfony.com/schema/dic/services http://symfony.com/schema/dic/services/services-1.0.xsd">

    <services>
        <service id="fxp_gluon.form.type_extension.date" class="Fxp\Component\Gluon\Form\Extension\DateExtension" public="true">
            <tag name="form.type_extension" priority="100" />
        </service>

        <service id="fxp_gluon.form.type_extension.choice" class="Fxp\Component\Gluon\Form\Extension\ChoiceExtension" public="true">
            <tag name="form.type_extension" priority="100" />
        </service>

        <service id="fxp_gluon.form.type_extension.button" class="Fxp\Component\Gluon\Form\Extension\ButtonExtension" public="true">
            <tag name="form.type_extension" priority="100" />
        </service>

        <service id="fxp_gluon.form.type_extension.checkbox" class="Fxp\Component\Gluon\Form\Extension\CheckboxExtension" public="true">
            <tag name="form.type_extension" priority="100" />
        </service>

        <service id="fxp_gluon.form.type_extension.textarea" class="Fxp\Component\Gluon\Form\Extension\TextareaExtension" public="true">
            <tag name="form.type_extension" priority="100" />
        </service>

        <service id="fxp_gluon.form.type_extension.collection" class="Fxp\Component\Gluon\Form\Extension\CollectionExtension" public="true">
            <tag name="form.type_extension" priority="100" />
        </service>

        <service id="fxp_gluon.form.type_extension.button_ripple" class="Fxp\Component\Gluon\Form\Extension\ButtonRippleExtension" public="true">
            <tag name="form.type_extension" priority="100" />
        </service>

        <service id="fxp_gluon.form.type_extension.floating_label.text" class="Fxp\Component\Gluon\Form\Extension\TextFloatingLabelExtension" public="true">
            <tag name="form.type_extension" priority="100" />
        </service>

        <service id="fxp_gluon.form.type_extension.floating_label.integer" class="Fxp\Component\Gluon\Form\Extension\IntegerFloatingLabelExtension" public="true">
            <tag name="form.type_extension" priority="100" />
        </service>

        <service id="fxp_gluon.form.type_extension.floating_label.money" class="Fxp\Component\Gluon\Form\Extension\MoneyFloatingLabelExtension" public="true">
            <tag name="form.type_extension" priority="100" />
        </service>

        <service id="fxp_gluon.form.type_extension.floating_label.number" class="Fxp\Component\Gluon\Form\Extension\NumberFloatingLabelExtension" public="true">
            <tag name="form.type_extension" priority="100" />
        </service>

        <service id="fxp_gluon.form.type_extension.floating_label.percent" class="Fxp\Component\Gluon\Form\Extension\PercentFloatingLabelExtension" public="true">
            <tag name="form.type_extension" priority="100" />
        </service>

        <service id="fxp_gluon.form.type_extension.floating_label.textarea" class="Fxp\Component\Gluon\Form\Extension\TextareaFloatingLabelExtension" public="true">
            <tag name="form.type_extension" priority="100" />
        </service>

        <service id="fxp_gluon.form.type_extension.floating_label.datetime" class="Fxp\Component\Gluon\Form\Extension\DatetimeFloatingLabelExtension" public="true">
            <tag name="form.type_extension" priority="100" />
        </service>

        <service id="fxp_gluon.form.type_extension.floating_label.date" class="Fxp\Component\Gluon\Form\Extension\DateFloatingLabelExtension" public="true">
            <tag name="form.type_extension" priority="100" />
        </service>

        <service id="fxp_gluon.form.type_extension.floating_label.time" class="Fxp\Component\Gluon\Form\Extension\TimeFloatingLabelExtension" public="true">
            <tag name="form.type_extension" priority="100" />
        </service>

        <service id="fxp_gluon.form.type_extension.floating_label.file" class="Fxp\Component\Gluon\Form\Extension\FileFloatingLabelExtension" public="true">
            <tag name="form.type_extension" priority="100" />
        </service>

        <service id="fxp_gluon.form.type_extension.floating_label.choice" class="Fxp\Component\Gluon\Form\Extension\ChoiceFloatingLabelExtension" public="true">
            <tag name="form.type_extension" priority="100" />
        </service>

        <service id="fxp_gluon.form.type_extension.floating_label.collection" class="Fxp\Component\Gluon\Form\Extension\CollectionFloatingLabelExtension" public="true">
            <tag name="form.type_extension" priority="100" />
        </service>
    </services>
</container>
